drakken/__init__.py
drakken/config.py
drakken/core.py
drakken/exceptions.py
drakken/message.py
drakken/middleware.py
drakken/mock.py
drakken/model.py
drakken/security.py
drakken/template.py
drakken-3.1.4.dist-info/LICENSE
drakken-3.1.4.dist-info/METADATA
drakken-3.1.4.dist-info/WHEEL
drakken-3.1.4.dist-info/top_level.txt
drakken-3.1.4.dist-info/RECORD
