Metadata-Version: 2.1
Name: drakken
Version: 3.1.4
Summary: Python web microframework
Author-email: Craig Howard <craig@seagrape.us>
Project-URL: Homepage, https://seagrape.us/drakken/index.html
Project-URL: Changelog, https://seagrape.us/drakken/HISTORY.html
Classifier: Programming Language :: Python :: 3
Classifier: License :: OSI Approved :: MIT License
Classifier: Operating System :: OS Independent
License-File: LICENSE
Requires-Dist: mako
Requires-Dist: parse
Requires-Dist: pyaml
Requires-Dist: sqlalchemy
